unifr_api_epuck/__init__.py
unifr_api_epuck/__main__.py
unifr_api_epuck/wrapper.py
unifr_api_epuck/communication/__init__.py
unifr_api_epuck/communication/client_communication.py
unifr_api_epuck/communication/host_communication.py
unifr_api_epuck/communication/socket_client_communication.py
unifr_api_epuck/epuck/__init__.py
unifr_api_epuck/epuck/best.pt
unifr_api_epuck/epuck/epuck.py
unifr_api_epuck/epuck/epuck_webots.py
unifr_api_epuck/epuck/epuck_wifi.py
unifr_api_epuck/epuck/models/__init__.py
unifr_api_epuck/epuck/models/common.py
unifr_api_epuck/epuck/models/helper.py
unifr_api_epuck/epuck/models/yolo.py
unifr_api_epuck/epuck/models/yolov5m.yaml
unifr_api_epuck/epuck/pi_puck/__init__.py
unifr_api_epuck/epuck/pi_puck/epuck_pipuck.py
unifr_api_epuck/epuck/pi_puck/epuck_pipuck_camera_configuration.py
unifr_api_epuck/epuck/pi_puck/ft903.py
unifr_api_epuck/flask_server_gui_communication/__init__.py
unifr_api_epuck/flask_server_gui_communication/app.py
unifr_api_epuck/flask_server_gui_communication/static/assets/index.cd9c0392.css
unifr_api_epuck/flask_server_gui_communication/static/assets/index.d6b79cc1.js
unifr_api_epuck/flask_server_gui_communication/static/assets/noCamera.ebb966a5.jpg
unifr_api_epuck/flask_server_gui_communication/templates/index.html
unifr_api_epuck/gui/__init__.py
unifr_api_epuck/gui/gui_epuck_camera.py
unifr_api_epuck/gui/gui_epuck_communication.py
unifr_api_epuck/gui/gui_epuck_main.py
unifr_api_epuck-1.3.11.dist-info/LICENSE
unifr_api_epuck-1.3.11.dist-info/METADATA
unifr_api_epuck-1.3.11.dist-info/WHEEL
unifr_api_epuck-1.3.11.dist-info/top_level.txt
unifr_api_epuck-1.3.11.dist-info/RECORD
