Metadata-Version: 2.1
Name: unifr_api_epuck
Version: 1.3.11
Summary: An API controller for the e-puck2 from GCtronic for Webots and Python3
Home-page: https://github.com/davidfrisch/UNIFR_API_EPUCK
Author: David Frischer
Author-email: david.frischer@unifr.ch
License: MIT
Classifier: License :: OSI Approved :: GNU Affero General Public License v3 or later (AGPLv3+)
Classifier: Programming Language :: Python :: 3.6
Classifier: Operating System :: OS Independent
License-File: LICENSE
Requires-Dist: Pillow
Requires-Dist: smbus2
Requires-Dist: numpy
Requires-Dist: Flask-Cors
Requires-Dist: Flask-SocketIO
Requires-Dist: simple-websocket
